[
  {
    "volatility": 0.9298928604413857,
    "long_coins": [
      "btc",
      "bnb",
      "ada",
      "sui",
      "wif",
      "jto",
      "tia",
      "op"
    ],
    "long_weights": {
      "btc": 0.2303608170651796,
      "bnb": 0.10994845470497434,
      "ada": 0.10994845470497434,
      "sui": 0.10994845470497434,
      "wif": 0.10994845470497434,
      "jto": 0.10994845470497434,
      "tia": 0.10994845470497434,
      "op": 0.10994845470497434
    },
    "short_coins": [
      "doge",
      "pump",
      "hype",
      "link",
      "aave",
      "pendle",
      "apt",
      "eth",
      "sol",
      "ltc",
      "trump",
      "pepe",
      "pengu",
      "bonk",
      "shib",
      "jup",
      "ondo",
      "kaito",
      "crv",
      "uni",
      "virtual",
      "ldo",
      "s",
      "wld",
      "xrp",
      "bera",
      "avax",
      "near",
      "ip",
      "ton",
      "arb",
      "dot",
      "xlm",
      "tao",
      "pyth",
      "w",
      "hbar",
      "fartcoin"
    ],
    "diff_returns_mean": -0.07778057302934599,
    "sharpe_ratio": -0.08364466094774234
  },
  {
    "volatility": 1.0161774794222673,
    "long_coins": [
      "btc",
      "bnb",
      "jup",
      "ada",
      "uni",
      "wif",
      "virtual",
      "dot"
    ],
    "long_weights": {
      "btc": 0.25857085465076757,
      "bnb": 0.10591844933560464,
      "jup": 0.10591844933560464,
      "ada": 0.10591844933560464,
      "uni": 0.10591844933560464,
      "wif": 0.10591844933560464,
      "virtual": 0.10591844933560464,
      "dot": 0.10591844933560464
    },
    "short_coins": [
      "doge",
      "pump",
      "hype",
      "link",
      "aave",
      "pendle",
      "sui",
      "apt",
      "eth",
      "sol",
      "ltc",
      "trump",
      "pepe",
      "pengu",
      "bonk",
      "shib",
      "ondo",
      "kaito",
      "crv",
      "jto",
      "ldo",
      "s",
      "op",
      "wld",
      "xrp",
      "bera",
      "avax",
      "near",
      "ip",
      "ton",
      "arb",
      "tia",
      "xlm",
      "tao",
      "pyth",
      "w",
      "hbar",
      "fartcoin"
    ],
    "diff_returns_mean": 0.017883955286037128,
    "sharpe_ratio": 0.017599243880315855
  },
  {
    "volatility": 1.0164981604208954,
    "long_coins": [
      "btc",
      "bnb",
      "ondo",
      "near",
      "dot",
      "jup",
      "virtual",
      "ada"
    ],
    "long_weights": {
      "btc": 0.23743223620107845,
      "bnb": 0.1089382519712745,
      "ondo": 0.1089382519712745,
      "near": 0.1089382519712745,
      "dot": 0.1089382519712745,
      "jup": 0.1089382519712745,
      "virtual": 0.1089382519712745,
      "ada": 0.1089382519712745
    },
    "short_coins": [
      "doge",
      "pump",
      "hype",
      "link",
      "aave",
      "pendle",
      "sui",
      "apt",
      "eth",
      "sol",
      "ltc",
      "trump",
      "pepe",
      "pengu",
      "wif",
      "bonk",
      "shib",
      "kaito",
      "crv",
      "uni",
      "jto",
      "ldo",
      "s",
      "op",
      "wld",
      "xrp",
      "bera",
      "avax",
      "ip",
      "ton",
      "arb",
      "tia",
      "xlm",
      "tao",
      "pyth",
      "w",
      "hbar",
      "fartcoin"
    ],
    "diff_returns_mean": -0.028593643003286057,
    "sharpe_ratio": -0.028129557058368365
  },
  {
    "volatility": 1.0183628224646784,
    "long_coins": [
      "btc",
      "bnb",
      "sui",
      "op",
      "arb",
      "ondo",
      "wld",
      "near"
    ],
    "long_weights": {
      "btc": 0.2589460467232747,
      "bnb": 0.08914369153955318,
      "sui": 0.12869470898726854,
      "op": 0.09572548357397162,
      "arb": 0.09663172047902063,
      "ondo": 0.15380787746605876,
      "wld": 0.12552506745835432,
      "near": 0.051525403772498216
    },
    "short_coins": [
      "doge",
      "pump",
      "hype",
      "link",
      "aave",
      "pendle",
      "apt",
      "eth",
      "sol",
      "ltc",
      "trump",
      "pepe",
      "pengu",
      "wif",
      "bonk",
      "shib",
      "jup",
      "kaito",
      "crv",
      "uni",
      "jto",
      "virtual",
      "ldo",
      "s",
      "ada",
      "xrp",
      "bera",
      "avax",
      "ip",
      "ton",
      "tia",
      "dot",
      "xlm",
      "tao",
      "pyth",
      "w",
      "hbar",
      "fartcoin"
    ],
    "diff_returns_mean": 0.013371164135934054,
    "sharpe_ratio": 0.01313005919007597
  },
  {
    "volatility": 1.0186656756963894,
    "long_coins": [
      "btc",
      "bnb",
      "dot",
      "doge",
      "sui",
      "jup",
      "arb",
      "near"
    ],
    "long_weights": {
      "btc": 0.26857112480516093,
      "bnb": 0.10448983931354842,
      "dot": 0.10448983931354842,
      "doge": 0.10448983931354842,
      "sui": 0.10448983931354842,
      "jup": 0.10448983931354842,
      "arb": 0.10448983931354842,
      "near": 0.10448983931354842
    },
    "short_coins": [
      "pump",
      "hype",
      "link",
      "aave",
      "pendle",
      "apt",
      "eth",
      "sol",
      "ltc",
      "trump",
      "pepe",
      "pengu",
      "wif",
      "bonk",
      "shib",
      "ondo",
      "kaito",
      "crv",
      "uni",
      "jto",
      "virtual",
      "ldo",
      "s",
      "ada",
      "op",
      "wld",
      "xrp",
      "bera",
      "avax",
      "ip",
      "ton",
      "tia",
      "xlm",
      "tao",
      "pyth",
      "w",
      "hbar",
      "fartcoin"
    ],
    "diff_returns_mean": -0.017400426641888827,
    "sharpe_ratio": -0.017081587273462796
  },
  {
    "volatility": 1.022786978198821,
    "long_coins": [
      "btc",
      "bnb",
      "doge",
      "tao",
      "bonk",
      "w",
      "op",
      "virtual"
    ],
    "long_weights": {
      "btc": 0.21535503164140757,
      "bnb": 0.11209213833694177,
      "doge": 0.11209213833694177,
      "tao": 0.11209213833694177,
      "bonk": 0.11209213833694177,
      "w": 0.11209213833694177,
      "op": 0.11209213833694177,
      "virtual": 0.11209213833694177
    },
    "short_coins": [
      "pump",
      "hype",
      "link",
      "aave",
      "pendle",
      "sui",
      "apt",
      "eth",
      "sol",
      "ltc",
      "trump",
      "pepe",
      "pengu",
      "wif",
      "shib",
      "jup",
      "ondo",
      "kaito",
      "crv",
      "uni",
      "jto",
      "ldo",
      "s",
      "ada",
      "wld",
      "xrp",
      "bera",
      "avax",
      "near",
      "ip",
      "ton",
      "arb",
      "tia",
      "dot",
      "xlm",
      "pyth",
      "hbar",
      "fartcoin"
    ],
    "diff_returns_mean": 0.06995003472514345,
    "sharpe_ratio": 0.06839159689765406
  },
  {
    "volatility": 1.025969248064248,
    "long_coins": [
      "btc",
      "bnb",
      "pepe",
      "arb",
      "hype",
      "ondo",
      "w",
      "tia"
    ],
    "long_weights": {
      "btc": 0.21938132123483298,
      "bnb": 0.11151695410930958,
      "pepe": 0.11151695410930958,
      "arb": 0.11151695410930958,
      "hype": 0.11151695410930958,
      "ondo": 0.11151695410930958,
      "w": 0.11151695410930958,
      "tia": 0.11151695410930958
    },
    "short_coins": [
      "doge",
      "pump",
      "link",
      "aave",
      "pendle",
      "sui",
      "apt",
      "eth",
      "sol",
      "ltc",
      "trump",
      "pengu",
      "wif",
      "bonk",
      "shib",
      "jup",
      "kaito",
      "crv",
      "uni",
      "jto",
      "virtual",
      "ldo",
      "s",
      "ada",
      "op",
      "wld",
      "xrp",
      "bera",
      "avax",
      "near",
      "ip",
      "ton",
      "dot",
      "xlm",
      "tao",
      "pyth",
      "hbar",
      "fartcoin"
    ],
    "diff_returns_mean": 0.0026818510221578076,
    "sharpe_ratio": 0.0026139682326909914
  },
  {
    "volatility": 1.0270154070774054,
    "long_coins": [
      "btc",
      "bnb",
      "bonk",
      "uni",
      "wld",
      "doge",
      "arb",
      "apt"
    ],
    "long_weights": {
      "btc": 0.2121090559427935,
      "bnb": 0.1125558491510295,
      "bonk": 0.1125558491510295,
      "uni": 0.1125558491510295,
      "wld": 0.1125558491510295,
      "doge": 0.1125558491510295,
      "arb": 0.1125558491510295,
      "apt": 0.1125558491510295
    },
    "short_coins": [
      "pump",
      "hype",
      "link",
      "aave",
      "pendle",
      "sui",
      "eth",
      "sol",
      "ltc",
      "trump",
      "pepe",
      "pengu",
      "wif",
      "shib",
      "jup",
      "ondo",
      "kaito",
      "crv",
      "jto",
      "virtual",
      "ldo",
      "s",
      "ada",
      "op",
      "xrp",
      "bera",
      "avax",
      "near",
      "ip",
      "ton",
      "tia",
      "dot",
      "xlm",
      "tao",
      "pyth",
      "w",
      "hbar",
      "fartcoin"
    ],
    "diff_returns_mean": 0.052676501812910614,
    "sharpe_ratio": 0.05129085839404591
  },
  {
    "volatility": 1.0306584518130801,
    "long_coins": [
      "btc",
      "bnb",
      "tao",
      "wif",
      "pepe",
      "dot",
      "virtual",
      "ldo"
    ],
    "long_weights": {
      "btc": 0.23319468318380154,
      "bnb": 0.10954361668802835,
      "tao": 0.10954361668802835,
      "wif": 0.10954361668802835,
      "pepe": 0.10954361668802835,
      "dot": 0.10954361668802835,
      "virtual": 0.10954361668802835,
      "ldo": 0.10954361668802835
    },
    "short_coins": [
      "doge",
      "pump",
      "hype",
      "link",
      "aave",
      "pendle",
      "sui",
      "apt",
      "eth",
      "sol",
      "ltc",
      "trump",
      "pengu",
      "bonk",
      "shib",
      "jup",
      "ondo",
      "kaito",
      "crv",
      "uni",
      "jto",
      "s",
      "ada",
      "op",
      "wld",
      "xrp",
      "bera",
      "avax",
      "near",
      "ip",
      "ton",
      "arb",
      "tia",
      "xlm",
      "pyth",
      "w",
      "hbar",
      "fartcoin"
    ],
    "diff_returns_mean": 0.06658782539122665,
    "sharpe_ratio": 0.06460707257005349
  },
  {
    "volatility": 1.0321924999066003,
    "long_coins": [
      "btc",
      "bnb",
      "s",
      "link",
      "ada",
      "ldo",
      "tia",
      "bonk"
    ],
    "long_weights": {
      "btc": 0.2052803370135873,
      "bnb": 0.07011087085172005,
      "s": 0.17669225932128474,
      "link": 0.06598272607855309,
      "ada": 0.12640789083283463,
      "ldo": 0.13486619808261013,
      "tia": 0.08195810205975927,
      "bonk": 0.1387016157596509
    },
    "short_coins": [
      "doge",
      "pump",
      "hype",
      "aave",
      "pendle",
      "sui",
      "apt",
      "eth",
      "sol",
      "ltc",
      "trump",
      "pepe",
      "pengu",
      "wif",
      "shib",
      "jup",
      "ondo",
      "kaito",
      "crv",
      "uni",
      "jto",
      "virtual",
      "op",
      "wld",
      "xrp",
      "bera",
      "avax",
      "near",
      "ip",
      "ton",
      "arb",
      "dot",
      "xlm",
      "tao",
      "pyth",
      "w",
      "hbar",
      "fartcoin"
    ],
    "diff_returns_mean": -0.09418953045678341,
    "sharpe_ratio": -0.09125190355995254
  }
]